irail/__init__.py
irail/cli.py
irail/commands/__init__.py
irail/commands/_cmd_vehicle.py
irail/commands/cmd_liveboard.py
irail/commands/cmd_route.py
irail/commands/cmd_vehicle.py
irail/commands/utils.py
irail-0.0.9.dist-info/DESCRIPTION.rst
irail-0.0.9.dist-info/METADATA
irail-0.0.9.dist-info/RECORD
irail-0.0.9.dist-info/WHEEL
irail-0.0.9.dist-info/entry_points.txt
irail-0.0.9.dist-info/metadata.json
irail-0.0.9.dist-info/top_level.txt
