Metadata-Version: 2.0
Name: irail
Version: 0.0.9
Summary: CLI to the iRail API
Home-page: http://github.com/Ben-Baert/iRail
Author: Ben Baert
Author-email: benbaert@tuta.io
License: MIT
Platform: UNKNOWN
Classifier: Development Status :: 3 - Alpha
Classifier: Programming Language :: Python :: 2.7
Classifier: Programming Language :: Python :: 3.5
Classifier: License :: OSI Approved :: MIT License
Classifier: Topic :: Utilities
Requires-Dist: click
Requires-Dist: requests
